pypidisk/__init__.py
pypidisk-1.0.0.dist-info/LICENSE
pypidisk-1.0.0.dist-info/METADATA
pypidisk-1.0.0.dist-info/WHEEL
pypidisk-1.0.0.dist-info/entry_points.txt
pypidisk-1.0.0.dist-info/top_level.txt
pypidisk-1.0.0.dist-info/RECORD
