Metadata-Version: 2.1
Name: pypidisk
Version: 1.0.0
Summary: CLI tool to know the amount of disk space PyPi packages are occupying.
Home-page: https://github.com/karishmashuklaa/pypidisk
Author: Karishma Shukla
Author-email: karishmashuklaa@gmail.com
License: MIT
Keywords: diskspace,dependencies,pypi,cli,pydisk,memory,modules,packages
Classifier: Intended Audience :: Developers
Classifier: Programming Language :: Python :: 3
Classifier: Operating System :: Unix
Classifier: Operating System :: MacOS :: MacOS X
Classifier: Operating System :: Microsoft :: Windows
License-File: LICENSE
